toke/__init__.py
toke/__pycache__/__init__.cpython-313.pyc
toke/__pycache__/toke.cpython-313.pyc
toke/toke.abi3.so
toke/toke.py
webtoken-0.1.0.dist-info/METADATA
webtoken-0.1.0.dist-info/WHEEL
webtoken-0.1.0.dist-info/RECORD
