Metadata-Version: 2.4
Name: webtoken
Version: 0.1.0
Summary: A Rust-backed JWT library
Requires-Python: >=3.11
